<?xml version="1.0" encoding="utf-8" ?>
<dwsync>
<file name="bg.js" server="D:/wamp/www/finotraco.com.br/loja1/" local="129896134800000000" remote="129896134800000000" />
<file name="cs.js" server="D:/wamp/www/finotraco.com.br/loja1/" local="129926717960000000" remote="129926717960000000" />
<file name="cy.js" server="D:/wamp/www/finotraco.com.br/loja1/" local="129896134800000000" remote="129896134800000000" />
<file name="da.js" server="D:/wamp/www/finotraco.com.br/loja1/" local="129896134800000000" remote="129896134800000000" />
<file name="de.js" server="D:/wamp/www/finotraco.com.br/loja1/" local="129896134800000000" remote="129896134800000000" />
<file name="el.js" server="D:/wamp/www/finotraco.com.br/loja1/" local="129896134800000000" remote="129896134800000000" />
<file name="en.js" server="D:/wamp/www/finotraco.com.br/loja1/" local="129896134800000000" remote="129896134800000000" />
<file name="eo.js" server="D:/wamp/www/finotraco.com.br/loja1/" local="129896134800000000" remote="129896134800000000" />
<file name="et.js" server="D:/wamp/www/finotraco.com.br/loja1/" local="129896134800000000" remote="129896134800000000" />
<file name="fa.js" server="D:/wamp/www/finotraco.com.br/loja1/" local="129896134800000000" remote="129896134800000000" />
<file name="fi.js" server="D:/wamp/www/finotraco.com.br/loja1/" local="129896134800000000" remote="129896134800000000" />
<file name="fr.js" server="D:/wamp/www/finotraco.com.br/loja1/" local="129926717960000000" remote="129926717960000000" />
<file name="gu.js" server="D:/wamp/www/finotraco.com.br/loja1/" local="129896134800000000" remote="129896134800000000" />
<file name="he.js" server="D:/wamp/www/finotraco.com.br/loja1/" local="129896134800000000" remote="129896134800000000" />
<file name="hr.js" server="D:/wamp/www/finotraco.com.br/loja1/" local="129896134800000000" remote="129896134800000000" />
<file name="it.js" server="D:/wamp/www/finotraco.com.br/loja1/" local="129896134800000000" remote="129896134800000000" />
<file name="nb.js" server="D:/wamp/www/finotraco.com.br/loja1/" local="129896134800000000" remote="129896134800000000" />
<file name="nl.js" server="D:/wamp/www/finotraco.com.br/loja1/" local="129896134800000000" remote="129896134800000000" />
<file name="no.js" server="D:/wamp/www/finotraco.com.br/loja1/" local="129896134800000000" remote="129896134800000000" />
<file name="pl.js" server="D:/wamp/www/finotraco.com.br/loja1/" local="129896134800000000" remote="129896134800000000" />
<file name="tr.js" server="D:/wamp/www/finotraco.com.br/loja1/" local="129896134800000000" remote="129896134800000000" />
<file name="ug.js" server="D:/wamp/www/finotraco.com.br/loja1/" local="129896134800000000" remote="129896134800000000" />
<file name="uk.js" server="D:/wamp/www/finotraco.com.br/loja1/" local="129896134800000000" remote="129896134800000000" />
<file name="vi.js" server="D:/wamp/www/finotraco.com.br/loja1/" local="129926716820000000" remote="129926716820000000" />
<file name="zh-cn.js" server="D:/wamp/www/finotraco.com.br/loja1/" local="129896134800000000" remote="129896134800000000" />
<file name="_translationstatus.txt" server="D:/wamp/www/finotraco.com.br/loja1/" local="129896134800000000" remote="129896134800000000" />
<file name="bg.js" server="//Biasutti/d/wamp/www/finotraco.com.br/loja1/" local="129896134800000000" remote="129896134800000000" />
<file name="cs.js" server="//Biasutti/d/wamp/www/finotraco.com.br/loja1/" local="129926717960000000" remote="129926717960000000" />
<file name="cy.js" server="//Biasutti/d/wamp/www/finotraco.com.br/loja1/" local="129896134800000000" remote="129896134800000000" />
<file name="da.js" server="//Biasutti/d/wamp/www/finotraco.com.br/loja1/" local="129896134800000000" remote="129896134800000000" />
<file name="de.js" server="//Biasutti/d/wamp/www/finotraco.com.br/loja1/" local="129896134800000000" remote="129896134800000000" />
<file name="el.js" server="//Biasutti/d/wamp/www/finotraco.com.br/loja1/" local="129896134800000000" remote="129896134800000000" />
<file name="en.js" server="//Biasutti/d/wamp/www/finotraco.com.br/loja1/" local="129896134800000000" remote="129896134800000000" />
<file name="eo.js" server="//Biasutti/d/wamp/www/finotraco.com.br/loja1/" local="129896134800000000" remote="129896134800000000" />
<file name="et.js" server="//Biasutti/d/wamp/www/finotraco.com.br/loja1/" local="129896134800000000" remote="129896134800000000" />
<file name="fa.js" server="//Biasutti/d/wamp/www/finotraco.com.br/loja1/" local="129896134800000000" remote="129896134800000000" />
<file name="fi.js" server="//Biasutti/d/wamp/www/finotraco.com.br/loja1/" local="129896134800000000" remote="129896134800000000" />
<file name="fr.js" server="//Biasutti/d/wamp/www/finotraco.com.br/loja1/" local="129926717960000000" remote="129926717960000000" />
<file name="gu.js" server="//Biasutti/d/wamp/www/finotraco.com.br/loja1/" local="129896134800000000" remote="129896134800000000" />
<file name="he.js" server="//Biasutti/d/wamp/www/finotraco.com.br/loja1/" local="129896134800000000" remote="129896134800000000" />
<file name="hr.js" server="//Biasutti/d/wamp/www/finotraco.com.br/loja1/" local="129896134800000000" remote="129896134800000000" />
<file name="it.js" server="//Biasutti/d/wamp/www/finotraco.com.br/loja1/" local="129896134800000000" remote="129896134800000000" />
<file name="nb.js" server="//Biasutti/d/wamp/www/finotraco.com.br/loja1/" local="129896134800000000" remote="129896134800000000" />
<file name="nl.js" server="//Biasutti/d/wamp/www/finotraco.com.br/loja1/" local="129896134800000000" remote="129896134800000000" />
<file name="no.js" server="//Biasutti/d/wamp/www/finotraco.com.br/loja1/" local="129896134800000000" remote="129896134800000000" />
<file name="pl.js" server="//Biasutti/d/wamp/www/finotraco.com.br/loja1/" local="129896134800000000" remote="129896134800000000" />
<file name="tr.js" server="//Biasutti/d/wamp/www/finotraco.com.br/loja1/" local="129896134800000000" remote="129896134800000000" />
<file name="ug.js" server="//Biasutti/d/wamp/www/finotraco.com.br/loja1/" local="129896134800000000" remote="129896134800000000" />
<file name="uk.js" server="//Biasutti/d/wamp/www/finotraco.com.br/loja1/" local="129896134800000000" remote="129896134800000000" />
<file name="vi.js" server="//Biasutti/d/wamp/www/finotraco.com.br/loja1/" local="129926716820000000" remote="129926716820000000" />
<file name="zh-cn.js" server="//Biasutti/d/wamp/www/finotraco.com.br/loja1/" local="129896134800000000" remote="129896134800000000" />
<file name="_translationstatus.txt" server="//Biasutti/d/wamp/www/finotraco.com.br/loja1/" local="129896134800000000" remote="129896134800000000" />
<file name="bg.js" server="D:/wamp/www/coreartepeliculas.com.br/loja1/" local="129896134800000000" remote="129896134800000000" />
<file name="cs.js" server="D:/wamp/www/coreartepeliculas.com.br/loja1/" local="129926717960000000" remote="129926717960000000" />
<file name="cy.js" server="D:/wamp/www/coreartepeliculas.com.br/loja1/" local="129896134800000000" remote="129896134800000000" />
<file name="da.js" server="D:/wamp/www/coreartepeliculas.com.br/loja1/" local="129896134800000000" remote="129896134800000000" />
<file name="de.js" server="D:/wamp/www/coreartepeliculas.com.br/loja1/" local="129896134800000000" remote="129896134800000000" />
<file name="el.js" server="D:/wamp/www/coreartepeliculas.com.br/loja1/" local="129896134800000000" remote="129896134800000000" />
<file name="en.js" server="D:/wamp/www/coreartepeliculas.com.br/loja1/" local="129896134800000000" remote="129896134800000000" />
<file name="eo.js" server="D:/wamp/www/coreartepeliculas.com.br/loja1/" local="129896134800000000" remote="129896134800000000" />
<file name="et.js" server="D:/wamp/www/coreartepeliculas.com.br/loja1/" local="129896134800000000" remote="129896134800000000" />
<file name="fa.js" server="D:/wamp/www/coreartepeliculas.com.br/loja1/" local="129896134800000000" remote="129896134800000000" />
<file name="fi.js" server="D:/wamp/www/coreartepeliculas.com.br/loja1/" local="129896134800000000" remote="129896134800000000" />
<file name="fr.js" server="D:/wamp/www/coreartepeliculas.com.br/loja1/" local="129926717960000000" remote="129926717960000000" />
<file name="gu.js" server="D:/wamp/www/coreartepeliculas.com.br/loja1/" local="129896134800000000" remote="129896134800000000" />
<file name="he.js" server="D:/wamp/www/coreartepeliculas.com.br/loja1/" local="129896134800000000" remote="129896134800000000" />
<file name="hr.js" server="D:/wamp/www/coreartepeliculas.com.br/loja1/" local="129896134800000000" remote="129896134800000000" />
<file name="it.js" server="D:/wamp/www/coreartepeliculas.com.br/loja1/" local="129896134800000000" remote="129896134800000000" />
<file name="nb.js" server="D:/wamp/www/coreartepeliculas.com.br/loja1/" local="129896134800000000" remote="129896134800000000" />
<file name="nl.js" server="D:/wamp/www/coreartepeliculas.com.br/loja1/" local="129896134800000000" remote="129896134800000000" />
<file name="no.js" server="D:/wamp/www/coreartepeliculas.com.br/loja1/" local="129896134800000000" remote="129896134800000000" />
<file name="pl.js" server="D:/wamp/www/coreartepeliculas.com.br/loja1/" local="129896134800000000" remote="129896134800000000" />
<file name="tr.js" server="D:/wamp/www/coreartepeliculas.com.br/loja1/" local="129896134800000000" remote="129896134800000000" />
<file name="ug.js" server="D:/wamp/www/coreartepeliculas.com.br/loja1/" local="129896134800000000" remote="129896134800000000" />
<file name="uk.js" server="D:/wamp/www/coreartepeliculas.com.br/loja1/" local="129896134800000000" remote="129896134800000000" />
<file name="vi.js" server="D:/wamp/www/coreartepeliculas.com.br/loja1/" local="129926716820000000" remote="129926716820000000" />
<file name="zh-cn.js" server="D:/wamp/www/coreartepeliculas.com.br/loja1/" local="129896134800000000" remote="129896134800000000" />
<file name="_translationstatus.txt" server="D:/wamp/www/coreartepeliculas.com.br/loja1/" local="129896134800000000" remote="129896134800000000" />
<file name="bg.js" server="ftp.coreartepeliculas.com.br/www/" local="129896098800000000" remote="129958616400000000" />
<file name="cs.js" server="ftp.coreartepeliculas.com.br/www/" local="129926681960000000" remote="129958616400000000" />
<file name="cy.js" server="ftp.coreartepeliculas.com.br/www/" local="129896098800000000" remote="129958616400000000" />
<file name="da.js" server="ftp.coreartepeliculas.com.br/www/" local="129896098800000000" remote="129958616400000000" />
<file name="de.js" server="ftp.coreartepeliculas.com.br/www/" local="129896098800000000" remote="129958616400000000" />
<file name="el.js" server="ftp.coreartepeliculas.com.br/www/" local="129896098800000000" remote="129958616400000000" />
<file name="en.js" server="ftp.coreartepeliculas.com.br/www/" local="129896098800000000" remote="129958616400000000" />
<file name="eo.js" server="ftp.coreartepeliculas.com.br/www/" local="129896098800000000" remote="129958616400000000" />
<file name="et.js" server="ftp.coreartepeliculas.com.br/www/" local="129896098800000000" remote="129958616400000000" />
<file name="fa.js" server="ftp.coreartepeliculas.com.br/www/" local="129896098800000000" remote="129958616400000000" />
<file name="fi.js" server="ftp.coreartepeliculas.com.br/www/" local="129896098800000000" remote="129958616400000000" />
<file name="fr.js" server="ftp.coreartepeliculas.com.br/www/" local="129926681960000000" remote="129958616400000000" />
<file name="gu.js" server="ftp.coreartepeliculas.com.br/www/" local="129896098800000000" remote="129958616400000000" />
<file name="he.js" server="ftp.coreartepeliculas.com.br/www/" local="129896098800000000" remote="129958616400000000" />
<file name="hr.js" server="ftp.coreartepeliculas.com.br/www/" local="129896098800000000" remote="129958616400000000" />
<file name="it.js" server="ftp.coreartepeliculas.com.br/www/" local="129896098800000000" remote="129958616400000000" />
<file name="nb.js" server="ftp.coreartepeliculas.com.br/www/" local="129896098800000000" remote="129958616400000000" />
<file name="nl.js" server="ftp.coreartepeliculas.com.br/www/" local="129896098800000000" remote="129958616400000000" />
<file name="no.js" server="ftp.coreartepeliculas.com.br/www/" local="129896098800000000" remote="129958616400000000" />
<file name="pl.js" server="ftp.coreartepeliculas.com.br/www/" local="129896098800000000" remote="129958616400000000" />
<file name="tr.js" server="ftp.coreartepeliculas.com.br/www/" local="129896098800000000" remote="129958616400000000" />
<file name="ug.js" server="ftp.coreartepeliculas.com.br/www/" local="129896098800000000" remote="129958616400000000" />
<file name="uk.js" server="ftp.coreartepeliculas.com.br/www/" local="129896098800000000" remote="129958616400000000" />
<file name="vi.js" server="ftp.coreartepeliculas.com.br/www/" local="129926680820000000" remote="129958616400000000" />
<file name="zh-cn.js" server="ftp.coreartepeliculas.com.br/www/" local="129896098800000000" remote="129958616400000000" />
<file name="_translationstatus.txt" server="ftp.coreartepeliculas.com.br/www/" local="129896098800000000" remote="129958617000000000" />
</dwsync>