<?xml version="1.0" encoding="utf-8" ?>
<dwsync>
<file name="delete.png" server="D:/wamp/www/joomla/" local="128894018460000000" remote="128894018460000000" />
<file name="delete.png" server="" local="128884705760000000" remote="128884705760000000" />
<file name="index.html" server="D:/wamp/www/joomla/" local="128894018460000000" remote="128894018460000000" />
<file name="index.html" server="" local="128884705760000000" remote="128884705760000000" />
<file name="medialist-details.css" server="D:/wamp/www/joomla/" local="128894018460000000" remote="128894018460000000" />
<file name="medialist-details.css" server="" local="128884705760000000" remote="128884705760000000" />
<file name="medialist-thumbs.css" server="D:/wamp/www/joomla/" local="128894018460000000" remote="128894018460000000" />
<file name="medialist-thumbs.css" server="" local="128884705760000000" remote="128884705760000000" />
<file name="mediamanager.css" server="D:/wamp/www/joomla/" local="128894018460000000" remote="128894018460000000" />
<file name="mediamanager.css" server="" local="128884705760000000" remote="128884705760000000" />
<file name="mediamanager.js" server="D:/wamp/www/joomla/" local="128894018460000000" remote="128894018460000000" />
<file name="mediamanager.js" server="" local="128884705760000000" remote="128884705760000000" />
<file name="mootree.gif" server="D:/wamp/www/joomla/" local="128894018460000000" remote="128894018460000000" />
<file name="mootree.gif" server="" local="128884705760000000" remote="128884705760000000" />
<file name="popup-imagelist.css" server="D:/wamp/www/joomla/" local="128894018460000000" remote="128894018460000000" />
<file name="popup-imagelist.css" server="" local="128884705760000000" remote="128884705760000000" />
<file name="popup-imagemanager.css" server="D:/wamp/www/joomla/" local="128894018460000000" remote="128894018460000000" />
<file name="popup-imagemanager.css" server="" local="128884705760000000" remote="128884705760000000" />
<file name="popup-imagemanager.js" server="D:/wamp/www/joomla/" local="128894018460000000" remote="128894018460000000" />
<file name="popup-imagemanager.js" server="" local="128884705760000000" remote="128884705760000000" />
<file name="progress.gif" server="D:/wamp/www/joomla/" local="128894018460000000" remote="128894018460000000" />
<file name="progress.gif" server="" local="128884705760000000" remote="128884705760000000" />
<file name="upload.png" server="D:/wamp/www/joomla/" local="128894018460000000" remote="128894018460000000" />
<file name="upload.png" server="" local="128884705760000000" remote="128884705760000000" />
</dwsync>